pmeshlab/__init__.py
pmeshlab/mesh.py
pmeshlab-0.0.5.dist-info/METADATA
pmeshlab-0.0.5.dist-info/WHEEL
pmeshlab-0.0.5.dist-info/top_level.txt
pmeshlab-0.0.5.dist-info/zip-safe
pmeshlab-0.0.5.dist-info/RECORD
