Metadata-Version: 2.1
Name: pmeshlab
Version: 0.0.5
Summary: 3D Mesh processing
Home-page: https://github.com/JeanMaximilienCadic/pmeshlab
Author: CADIC Jean Maximilien
Author-email: contact@cadic.jp
License: : OSI Approved :: MIT License
Keywords: 3D mesh,point cloud
Requires-Dist: pymeshlab
Requires-Dist: nmesh (>=0.1.4)
Requires-Dist: gnutools-python
